tnflux/__init__.py
tnflux/tnf2d.py
tnflux-0.9.2.data/data/LICENSE
tnflux-0.9.2.data/data/eq38.jpg
tnflux-0.9.2.data/data/eq38_hor.jpg
tnflux-0.9.2.data/data/jan1981.jpg
tnflux-0.9.2.data/data/psnh_mon_hist_waf300_198101.jpg
tnflux-0.9.2.dist-info/LICENSE
tnflux-0.9.2.dist-info/METADATA
tnflux-0.9.2.dist-info/WHEEL
tnflux-0.9.2.dist-info/top_level.txt
tnflux-0.9.2.dist-info/RECORD
