Metadata-Version: 2.1
Name: tnflux
Version: 0.9.2
Summary: Caculating the T-N Wave Activity Flux derived by Takaya and Nakamura (JAS,2001).
Home-page: https://github.com/jokervTv/T-N_Wave-Activity-Flux
Author: Lai Sheng<laish12@lzu.edu.cn>, Yongpeng Zhang<zhangyp6603@outlook.com>
Author-email: laish12@lzu.edu.cn
Maintainer: Yongpeng Zhang
Maintainer-email: zhangyp6603@outlook.com
License: MIT License
Keywords: tn wave activity flux
Platform: any
Classifier: Development Status :: 4 - Beta
Classifier: Intended Audience :: Science/Research
Classifier: Topic :: Scientific/Engineering :: Atmospheric Science
Classifier: License :: OSI Approved :: MIT License
Classifier: Programming Language :: Python :: 3
Requires-Dist: numpy
